SEQ/decode/decode.v
// DECODE BLOCK

module decode(clk, icode, rA, rB, valA, valB);

    input clk;
    input [3:0] icode;
    input [3:0] rA;
    input [3:0] rB;

    output reg [63:0] valA;
    output reg [63:0] valB;

    reg [63:0] Reg_File[0:14];

    integer i;

    initial
    begin
        valA = 64'd0;
        valB = 64'd0;
    end

    // instruction codes
    // Constant values used in HCL descriptions.
    parameter IHALT   = 4'd0;
    parameter INOP    = 4'd1;
    parameter IRRMOVQ = 4'd2; //rrmovq and  cmovXX
    parameter IIRMOVQ = 4'd3;
    parameter IRMMOVQ = 4'd4;
    parameter IMRMOVQ = 4'd5;
    parameter IOPQ    = 4'd6;
    parameter IJXX    = 4'd7;
    parameter ICALL   = 4'd8;
    parameter IRET    = 4'd9;
    parameter IPUSHQ  = 4'd10;
    parameter IPOPQ   = 4'd11;

    // registers
    parameter Register_rax = 4'd0;
    parameter Register_rcx = 4'd1;
    parameter Register_rdx = 4'd2;
    parameter Register_rbx = 4'd3;
    parameter RRSP         = 4'd4;
    parameter Register_rbp = 4'd5;
    parameter Register_rsi = 4'd6;
    parameter Register_rdi = 4'd7;
    parameter Register_r8  = 4'd8;
    parameter Register_r9  = 4'd9;
    parameter Register_r10 = 4'd10;
    parameter Register_r11 = 4'd11;
    parameter Register_r12 = 4'd12;
    parameter Register_r13 = 4'd13;
    parameter Register_r14 = 4'd14;
    parameter RNONE        = 4'd15;

    always@(posedge clk)
    begin

        $readmemh("reg_file.txt", Reg_File);
        
    end

    always@(*)
    begin

        if(clk == 1)
        begin
        
            if (icode == IRRMOVQ)
            begin

                // valA ← R[rA]
                valA = Reg_File[rA];

            end
            // rmmovq
            else if (icode == IRMMOVQ)
            begin

                // valA ← R[rA]
                valA = Reg_File[rA];
                
                // valB ← R[rB]
                valB = Reg_File[rB];

            end
            // mrmovq
            else if (icode == IMRMOVQ)
            begin

                // valB ← R[rB]
                valB = Reg_File[rB];

            end
            //Opq
            else if (icode == IOPQ)
            begin

                // valA ← R[rA]
                valA = Reg_File[rA];
                
                // valB ← R[rB]
                valB = Reg_File[rB];    

            end
            else if (icode == ICALL)
            begin

                //valB ← R[ %rsp ]
                valB = Reg_File[RRSP];    

            end
            //ret
            else if (icode == IRET)
            begin

                // valA ← R[ %rsp ]
                valA = Reg_File[RRSP];

                // valB ← R[ %rsp ]
                valB = Reg_File[RRSP];

            end
            //pushq
            else if (icode == IPUSHQ)
            begin

                // valA ← R[rA]
                valA = Reg_File[rA];

                // valB ← R[ %rsp ]
                valB = Reg_File[RRSP];

            end
            //popq
            else if (icode == IPOPQ)
            begin

                // valA ← R[ %rsp ]
                valA = Reg_File[RRSP];

                // valB ← R[ %rsp ]
                valB = Reg_File[RRSP];   

            end
        end
    end

endmodule

SEQ/decode/decode_tb.v
`timescale 1ns / 10ps

module decode_tb();

    reg clk;
    reg [3:0] icode;
    reg [3:0] rA;
    reg [3:0] rB;

    wire [63:0] valA;
    wire [63:0] valB;

    decode UUT(clk, icode, rA, rB, valA, valB);

    //creating clk
    initial
    begin
        clk = 0;
        repeat (20)  #10 clk = ~clk;
    end

    initial
    begin

        $dumpfile("decode_tb.vcd");
        $dumpvars(0, decode_tb);

        clk=0;
        icode=4'd0;
        rA=4'd0;
        rB=4'd0;

    end

    initial
    begin

        #10
        icode=4'd2;rA=4'd0;rB=4'd0;

        #20
        icode=4'd3;rA=4'd1;rB=4'd2;

        #20
        icode=4'd4;rA=4'd3;rB=4'd4;

        #20
        icode=4'd5;rA=4'd4;rB=4'd10;

        #20
        icode=4'd6;rA=4'd11;rB=4'd5;

        #20
        icode=4'd7;rA=4'd6;rB=4'd7;

        #20
        icode=4'd8;rA=4'd6;rB=4'd7;

        #20
        icode=4'd9;rA=4'd7;rB=4'd8;

        #20
        icode=4'd10;rA=4'd9;rB=4'd10;

        #20
        icode=4'd11;rA=4'd0;rB=4'd1;
    end

    initial 
    begin
		$monitor($time, "\tclk = %d icode = %b rA = %b rB = %b\n\t\t\tvalA = %g valB = %g\n", clk,icode, rA, rB, valA, valB);
	end

endmodule

SEQ/decode/decode_tb.vcd
$date
	Sun Feb 19 18:31:45 2023
$end
$version
	Icarus Verilog
$end
$timescale
	10ps
$end
$scope module decode_tb $end
$var wire 64 ! valB [63:0] $end
$var wire 64 " valA [63:0] $end
$var reg 1 # clk $end
$var reg 4 $ icode [3:0] $end
$var reg 4 % rA [3:0] $end
$var reg 4 & rB [3:0] $end
$scope module UUT $end
$var wire 1 # clk $end
$var wire 4 ' icode [3:0] $end
$var wire 4 ( rA [3:0] $end
$var wire 4 ) rB [3:0] $end
$var reg 64 * valA [63:0] $end
$var reg 64 + valB [63:0] $end
$upscope $end
$upscope $end
$enddefinitions $end
#0
$dumpvars
b0 +
b0 *
b0 )
b0 (
b0 '
b0 &
b0 %
b0 $
0#
b0 "
b0 !
$end
#1000
b1 "
b1 *
b10 $
b10 '
1#
#2000
0#
#3000
1#
b10 &
b10 )
b1 %
b1 (
b11 $
b11 '
#4000
0#
#5000
b1 !
b1 +
1#
b100 &
b100 )
b11 %
b11 (
b100 $
b100 '
#6000
0#
#7000
1#
b1010 &
b1010 )
b100 %
b100 (
b101 $
b101 '
#8000
0#
#9000
1#
b101 &
b101 )
b1011 %
b1011 (
b110 $
b110 '
#10000
0#
#11000
1#
b111 &
b111 )
b110 %
b110 (
b111 $
b111 '
#12000
0#
#13000
1#
b1000 $
b1000 '
#14000
0#
#15000
1#
b1000 &
b1000 )
b111 %
b111 (
b1001 $
b1001 '
#16000
0#
#17000
1#
b1010 &
b1010 )
b1001 %
b1001 (
b1010 $
b1010 '
#18000
0#
#19000
1#
b1 &
b1 )
b0 %
b0 (
b1011 $
b1011 '
