SEQ/seq/write_back.v
// WRITE BACK BLOCK

module write_back(clk, icode, rA, rB, cnd, valE, valM);

    input clk;
    input [3:0] icode;
    input [3:0] rA;
    input [3:0] rB;
    input cnd;
    input [63:0] valE;
    input [63:0] valM;

    reg [3:0] dstE;
    reg [3:0] dstM;

    reg [63:0] Reg_File[0:14];

    integer i;

    initial
    begin
        dstE = 4'd15;
        dstM = 4'd15;
    end

    // instruction codes
    // Constant values used in HCL descriptions.
    parameter IHALT   = 4'd0;
    parameter INOP    = 4'd1;
    parameter IRRMOVQ = 4'd2; //rrmovq and  cmovXX
    parameter IIRMOVQ = 4'd3;
    parameter IRMMOVQ = 4'd4;
    parameter IMRMOVQ = 4'd5;
    parameter IOPQ    = 4'd6;
    parameter IJXX    = 4'd7;
    parameter ICALL   = 4'd8;
    parameter IRET    = 4'd9;
    parameter IPUSHQ  = 4'd10;
    parameter IPOPQ   = 4'd11;

    // registers
    parameter Register_rax = 4'd0;
    parameter Register_rcx = 4'd1;
    parameter Register_rdx = 4'd2;
    parameter Register_rbx = 4'd3;
    parameter RRSP         = 4'd4;
    parameter Register_rbp = 4'd5;
    parameter Register_rsi = 4'd6;
    parameter Register_rdi = 4'd7;
    parameter Register_r8  = 4'd8;
    parameter Register_r9  = 4'd9;
    parameter Register_r10 = 4'd10;
    parameter Register_r11 = 4'd11;
    parameter Register_r12 = 4'd12;
    parameter Register_r13 = 4'd13;
    parameter Register_r14 = 4'd14;
    parameter RNONE        = 4'd15;


    always@(*)
    begin
        if(clk==1)
            $readmemh("reg_file.txt", Reg_File);
        
    end

    always@(*)
    begin
        if(clk == 0)
        begin
            $writememh("reg_file.txt", Reg_File);
        end
    end

    always@(negedge clk)
    begin

        //rrmovq and  cmovXX
        if (icode == IRRMOVQ && cnd == 1)
        begin

            // R[rB] ← valE
            dstE = rB;
            Reg_File[dstE] = valE;             

        end
        //irmovq
        else if (icode == IIRMOVQ)
        begin

            // R[rB] ← valE
            dstE = rB;
            Reg_File[dstE] = valE;            

        end
        // mrmovq
        else if (icode == IMRMOVQ)
        begin

            // R[rA] ← valM
            dstM = rA;
            Reg_File[dstM] = valM;
                
        end
        //Opq
        else if (icode == IOPQ)
        begin
            
            // R[rB] ← valE
            dstE = rB;
            Reg_File[dstE] = valE;                

        end
        //call
        else if (icode == ICALL)
        begin

            // R[ %rsp ] ← valE
            dstE = RRSP;
            Reg_File[dstE] = valE;      

        end
        //ret
        else if (icode == IRET)
        begin

            // R[ %rsp ] ← valE
            dstE = RRSP;
            Reg_File[dstE] = valE;    

        end
        //pushq
        else if (icode == IPUSHQ)
        begin
            
            // R[ %rsp ] ← valE
            dstE = RRSP;
            Reg_File[dstE] = valE;                   

        end
        //popq
        else if (icode == IPOPQ)
        begin

            // R[ %rsp ] ← valE
            dstE = RRSP;
            Reg_File[dstE] = valE;

            // R[rA] ← valM
            dstM = rA;   
            Reg_File[dstM] = valM; 

        end

    end


endmodule

SEQ/write_back/write_back_tb.v
`timescale 1ns / 10ps

module write_back_tb();

    reg clk;
    reg [3:0] icode;
    reg [3:0] rA;
    reg [3:0] rB;
    reg cnd;
    reg [63:0] valE;
    reg [63:0] valM;

    write_back UUT(clk, icode, rA, rB, cnd, valE, valM);

    //creating clk
    initial
    begin
        clk = 0;
        repeat (25)  #10 clk = ~clk;
    end

    initial
    begin

        $dumpfile("write_back_tb.vcd");
        $dumpvars(0, write_back_tb);

        clk=0;
        icode=4'd0;
        rA=4'd0;
        rB=4'd0;
        cnd=0;
        valE=64'd0;
        valM=64'd0;

    end

    initial
    begin

        #10
        icode=4'd2;rA=4'd0;rB=4'd1;cnd=0;valE=64'd20;valM=64'd50;

        #20
        icode=4'd2;rA=4'd0;rB=4'd1;cnd=1;valE=64'd20;valM=64'd50;

        #20
        icode=4'd3;rA=4'd1;rB=4'd2;cnd=0;valE=64'd100;valM=64'd100;

        #20
        icode=4'd3;rA=4'd1;rB=4'd2;cnd=1;valE=64'd100;valM=64'd100;

        #20
        icode=4'd4;rA=4'd3;rB=4'd4;cnd=1;valE=64'd256;valM=64'd10;

        #20
        icode=4'd5;rA=4'd5;rB=4'd4;cnd=1;valE=64'd1024;valM=64'd51;

        #20
        icode=4'd6;rA=4'd6;rB=4'd7;cnd=0;valE=64'd91;valM=64'd1;

        #20
        icode=4'd7;rA=4'd8;rB=4'd7;cnd=0;valE=64'd34;valM=64'd0;

        #20
        icode=4'd8;rA=4'd1;rB=4'd9;cnd=1;valE=64'd720;valM=64'd3;

        #20
        icode=4'd9;rA=4'd8;rB=4'd10;cnd=0;valE=64'd2222;valM=64'd189302;

        #20
        icode=4'd10;rA=4'd11;rB=4'd12;cnd=1;valE=64'd77821;valM=64'd3321;

        #20
        icode=4'd11;rA=4'd13;rB=4'd14;cnd=1;valE=64'd728782;valM=64'd5849;
        
    end

    initial 
    begin
        $monitor($time, "\tclk = %d icode = %b rA = %b rB = %b Cnd = %b valE = %g valM = %g\n",clk,icode,rA,rB,cnd,valE,valM);
    end
endmodule

SEQ/write_back/write_back_tb.vcd
$date
	Sun Feb 19 18:35:34 2023
$end
$version
	Icarus Verilog
$end
$timescale
	10ps
$end
$scope module write_back_tb $end
$var reg 1 ! clk $end
$var reg 1 " cnd $end
$var reg 4 # icode [3:0] $end
$var reg 4 $ rA [3:0] $end
$var reg 4 % rB [3:0] $end
$var reg 64 & valE [63:0] $end
$var reg 64 ' valM [63:0] $end
$scope module UUT $end
$var wire 1 ! clk $end
$var wire 1 " cnd $end
$var wire 4 ( icode [3:0] $end
$var wire 4 ) rA [3:0] $end
$var wire 4 * rB [3:0] $end
$var wire 64 + valE [63:0] $end
$var wire 64 , valM [63:0] $end
$var reg 4 - dstE [3:0] $end
$var reg 4 . dstM [3:0] $end
$upscope $end
$upscope $end
$enddefinitions $end
#0
$dumpvars
b1111 .
b1111 -
b0 ,
b0 +
b0 *
b0 )
b0 (
b0 '
b0 &
b0 %
b0 $
b0 #
0"
0!
$end
#1000
b110010 '
b110010 ,
b10100 &
b10100 +
b1 %
b1 *
b10 #
b10 (
1!
#2000
0!
#3000
1!
1"
#4000
b1 -
0!
#5000
1!
b1100100 '
b1100100 ,
b1100100 &
b1100100 +
0"
b10 %
b10 *
b1 $
b1 )
b11 #
b11 (
#6000
b10 -
0!
#7000
1!
1"
#8000
0!
#9000
1!
b1010 '
b1010 ,
b100000000 &
b100000000 +
b100 %
b100 *
b11 $
b11 )
b100 #
b100 (
#10000
0!
#11000
1!
b110011 '
b110011 ,
b10000000000 &
b10000000000 +
b101 $
b101 )
b101 #
b101 (
#12000
b101 .
0!
#13000
1!
b1 '
b1 ,
b1011011 &
b1011011 +
0"
b111 %
b111 *
b110 $
b110 )
b110 #
b110 (
#14000
b111 -
0!
#15000
1!
b0 '
b0 ,
b100010 &
b100010 +
b1000 $
b1000 )
b111 #
b111 (
#16000
0!
#17000
1!
b11 '
b11 ,
b1011010000 &
b1011010000 +
1"
b1001 %
b1001 *
b1 $
b1 )
b1000 #
b1000 (
#18000
b100 -
0!
#19000
1!
b101110001101110110 '
b101110001101110110 ,
b100010101110 &
b100010101110 +
0"
b1010 %
b1010 *
b1000 $
b1000 )
b1001 #
b1001 (
#20000
0!
#21000
1!
b110011111001 '
b110011111001 ,
b10010111111111101 &
b10010111111111101 +
1"
b1100 %
b1100 *
b1011 $
b1011 )
b1010 #
b1010 (
#22000
0!
#23000
1!
b1011011011001 '
b1011011011001 ,
b10110001111011001110 &
b10110001111011001110 +
b1110 %
b1110 *
b1101 $
b1101 )
b1011 #
b1011 (
#24000
b1101 .
0!
